gradientify/__init__.py
gradientify-2.0.9.dist-info/METADATA
gradientify-2.0.9.dist-info/WHEEL
gradientify-2.0.9.dist-info/top_level.txt
gradientify-2.0.9.dist-info/RECORD
