Metadata-Version: 2.1
Name: gradientify
Version: 2.0.9
Summary: A Python package for gradient colors
Home-page: https://vanishnet.netlify.app/
Author: virtual
Requires-Python: >=3.11
